[
  {
    "time_start": "2026-06-05T00:00:00+02:00",
    "SEK_per_kWh": 0.78182
  },
  {
    "time_start": "2026-06-05T01:00:00+02:00",
    "SEK_per_kWh": 0.488537
  },
  {
    "time_start": "2026-06-05T02:00:00+02:00",
    "SEK_per_kWh": 0.488675
  },
  {
    "time_start": "2026-06-05T03:00:00+02:00",
    "SEK_per_kWh": 0.7321
  },
  {
    "time_start": "2026-06-05T04:00:00+02:00",
    "SEK_per_kWh": 0.519137
  },
  {
    "time_start": "2026-06-05T05:00:00+02:00",
    "SEK_per_kWh": 0.594502
  },
  {
    "time_start": "2026-06-05T06:00:00+02:00",
    "SEK_per_kWh": 0.896948
  },
  {
    "time_start": "2026-06-05T07:00:00+02:00",
    "SEK_per_kWh": 1.154325
  },
  {
    "time_start": "2026-06-05T08:00:00+02:00",
    "SEK_per_kWh": 1.087013
  },
  {
    "time_start": "2026-06-05T09:00:00+02:00",
    "SEK_per_kWh": 0.93334
  },
  {
    "time_start": "2026-06-05T10:00:00+02:00",
    "SEK_per_kWh": 0.812335
  },
  {
    "time_start": "2026-06-05T11:00:00+02:00",
    "SEK_per_kWh": 0.6331
  },
  {
    "time_start": "2026-06-05T12:00:00+02:00",
    "SEK_per_kWh": 0.356027
  },
  {
    "time_start": "2026-06-05T13:00:00+02:00",
    "SEK_per_kWh": 0.26056
  },
  {
    "time_start": "2026-06-05T14:00:00+02:00",
    "SEK_per_kWh": 0.224305
  },
  {
    "time_start": "2026-06-05T15:00:00+02:00",
    "SEK_per_kWh": 0.286508
  },
  {
    "time_start": "2026-06-05T16:00:00+02:00",
    "SEK_per_kWh": 0.650015
  },
  {
    "time_start": "2026-06-05T17:00:00+02:00",
    "SEK_per_kWh": 1.019753
  },
  {
    "time_start": "2026-06-05T18:00:00+02:00",
    "SEK_per_kWh": 1.266952
  },
  {
    "time_start": "2026-06-05T19:00:00+02:00",
    "SEK_per_kWh": 1.47331
  },
  {
    "time_start": "2026-06-05T20:00:00+02:00",
    "SEK_per_kWh": 1.69734
  },
  {
    "time_start": "2026-06-05T21:00:00+02:00",
    "SEK_per_kWh": 1.75612
  },
  {
    "time_start": "2026-06-05T22:00:00+02:00",
    "SEK_per_kWh": 1.586265
  },
  {
    "time_start": "2026-06-05T23:00:00+02:00",
    "SEK_per_kWh": 1.438822
  }
]