[
  {
    "time_start": "2026-04-24T00:00:00+02:00",
    "SEK_per_kWh": 0.427855
  },
  {
    "time_start": "2026-04-24T01:00:00+02:00",
    "SEK_per_kWh": 0.43514
  },
  {
    "time_start": "2026-04-24T02:00:00+02:00",
    "SEK_per_kWh": 0.440405
  },
  {
    "time_start": "2026-04-24T03:00:00+02:00",
    "SEK_per_kWh": 0.446365
  },
  {
    "time_start": "2026-04-24T04:00:00+02:00",
    "SEK_per_kWh": 0.467977
  },
  {
    "time_start": "2026-04-24T05:00:00+02:00",
    "SEK_per_kWh": 0.493293
  },
  {
    "time_start": "2026-04-24T06:00:00+02:00",
    "SEK_per_kWh": 0.558918
  },
  {
    "time_start": "2026-04-24T07:00:00+02:00",
    "SEK_per_kWh": 0.579935
  },
  {
    "time_start": "2026-04-24T08:00:00+02:00",
    "SEK_per_kWh": 0.61091
  },
  {
    "time_start": "2026-04-24T09:00:00+02:00",
    "SEK_per_kWh": 0.459885
  },
  {
    "time_start": "2026-04-24T10:00:00+02:00",
    "SEK_per_kWh": 0.177632
  },
  {
    "time_start": "2026-04-24T11:00:00+02:00",
    "SEK_per_kWh": 0.06309
  },
  {
    "time_start": "2026-04-24T12:00:00+02:00",
    "SEK_per_kWh": 0.052187
  },
  {
    "time_start": "2026-04-24T13:00:00+02:00",
    "SEK_per_kWh": 0.044575
  },
  {
    "time_start": "2026-04-24T14:00:00+02:00",
    "SEK_per_kWh": 0.041095
  },
  {
    "time_start": "2026-04-24T15:00:00+02:00",
    "SEK_per_kWh": 0.057908
  },
  {
    "time_start": "2026-04-24T16:00:00+02:00",
    "SEK_per_kWh": 0.09312
  },
  {
    "time_start": "2026-04-24T17:00:00+02:00",
    "SEK_per_kWh": 0.40017
  },
  {
    "time_start": "2026-04-24T18:00:00+02:00",
    "SEK_per_kWh": 0.91089
  },
  {
    "time_start": "2026-04-24T19:00:00+02:00",
    "SEK_per_kWh": 1.119988
  },
  {
    "time_start": "2026-04-24T20:00:00+02:00",
    "SEK_per_kWh": 1.227223
  },
  {
    "time_start": "2026-04-24T21:00:00+02:00",
    "SEK_per_kWh": 1.033698
  },
  {
    "time_start": "2026-04-24T22:00:00+02:00",
    "SEK_per_kWh": 0.873333
  },
  {
    "time_start": "2026-04-24T23:00:00+02:00",
    "SEK_per_kWh": 0.698423
  }
]