[
  {
    "time_start": "2026-06-28T00:00:00+02:00",
    "SEK_per_kWh": 0.829168
  },
  {
    "time_start": "2026-06-28T01:00:00+02:00",
    "SEK_per_kWh": 0.807423
  },
  {
    "time_start": "2026-06-28T02:00:00+02:00",
    "SEK_per_kWh": 0.793085
  },
  {
    "time_start": "2026-06-28T03:00:00+02:00",
    "SEK_per_kWh": 0.762798
  },
  {
    "time_start": "2026-06-28T04:00:00+02:00",
    "SEK_per_kWh": 0.75317
  },
  {
    "time_start": "2026-06-28T05:00:00+02:00",
    "SEK_per_kWh": 0.734393
  },
  {
    "time_start": "2026-06-28T06:00:00+02:00",
    "SEK_per_kWh": 0.538438
  },
  {
    "time_start": "2026-06-28T07:00:00+02:00",
    "SEK_per_kWh": 0.42217
  },
  {
    "time_start": "2026-06-28T08:00:00+02:00",
    "SEK_per_kWh": 0.460002
  },
  {
    "time_start": "2026-06-28T09:00:00+02:00",
    "SEK_per_kWh": 0.350113
  },
  {
    "time_start": "2026-06-28T10:00:00+02:00",
    "SEK_per_kWh": 0.187025
  },
  {
    "time_start": "2026-06-28T11:00:00+02:00",
    "SEK_per_kWh": 0.197147
  },
  {
    "time_start": "2026-06-28T12:00:00+02:00",
    "SEK_per_kWh": 0.146805
  },
  {
    "time_start": "2026-06-28T13:00:00+02:00",
    "SEK_per_kWh": 0.147888
  },
  {
    "time_start": "2026-06-28T14:00:00+02:00",
    "SEK_per_kWh": 0.180978
  },
  {
    "time_start": "2026-06-28T15:00:00+02:00",
    "SEK_per_kWh": 0.225467
  },
  {
    "time_start": "2026-06-28T16:00:00+02:00",
    "SEK_per_kWh": 0.397787
  },
  {
    "time_start": "2026-06-28T17:00:00+02:00",
    "SEK_per_kWh": 0.77955
  },
  {
    "time_start": "2026-06-28T18:00:00+02:00",
    "SEK_per_kWh": 0.975588
  },
  {
    "time_start": "2026-06-28T19:00:00+02:00",
    "SEK_per_kWh": 1.113237
  },
  {
    "time_start": "2026-06-28T20:00:00+02:00",
    "SEK_per_kWh": 1.178117
  },
  {
    "time_start": "2026-06-28T21:00:00+02:00",
    "SEK_per_kWh": 1.112407
  },
  {
    "time_start": "2026-06-28T22:00:00+02:00",
    "SEK_per_kWh": 1.004878
  },
  {
    "time_start": "2026-06-28T23:00:00+02:00",
    "SEK_per_kWh": 0.966548
  }
]