[
  {
    "time_start": "2025-11-16T00:00:00+01:00",
    "SEK_per_kWh": 0.32637
  },
  {
    "time_start": "2025-11-16T01:00:00+01:00",
    "SEK_per_kWh": 0.321368
  },
  {
    "time_start": "2025-11-16T02:00:00+01:00",
    "SEK_per_kWh": 0.335513
  },
  {
    "time_start": "2025-11-16T03:00:00+01:00",
    "SEK_per_kWh": 0.33057
  },
  {
    "time_start": "2025-11-16T04:00:00+01:00",
    "SEK_per_kWh": 0.333235
  },
  {
    "time_start": "2025-11-16T05:00:00+01:00",
    "SEK_per_kWh": 0.34477
  },
  {
    "time_start": "2025-11-16T06:00:00+01:00",
    "SEK_per_kWh": 0.365727
  },
  {
    "time_start": "2025-11-16T07:00:00+01:00",
    "SEK_per_kWh": 0.383635
  },
  {
    "time_start": "2025-11-16T08:00:00+01:00",
    "SEK_per_kWh": 0.41893
  },
  {
    "time_start": "2025-11-16T09:00:00+01:00",
    "SEK_per_kWh": 0.431593
  },
  {
    "time_start": "2025-11-16T10:00:00+01:00",
    "SEK_per_kWh": 0.456865
  },
  {
    "time_start": "2025-11-16T11:00:00+01:00",
    "SEK_per_kWh": 0.476367
  },
  {
    "time_start": "2025-11-16T12:00:00+01:00",
    "SEK_per_kWh": 0.658033
  },
  {
    "time_start": "2025-11-16T13:00:00+01:00",
    "SEK_per_kWh": 0.833633
  },
  {
    "time_start": "2025-11-16T14:00:00+01:00",
    "SEK_per_kWh": 0.87629
  },
  {
    "time_start": "2025-11-16T15:00:00+01:00",
    "SEK_per_kWh": 0.936525
  },
  {
    "time_start": "2025-11-16T16:00:00+01:00",
    "SEK_per_kWh": 1.087595
  },
  {
    "time_start": "2025-11-16T17:00:00+01:00",
    "SEK_per_kWh": 1.166152
  },
  {
    "time_start": "2025-11-16T18:00:00+01:00",
    "SEK_per_kWh": 1.148543
  },
  {
    "time_start": "2025-11-16T19:00:00+01:00",
    "SEK_per_kWh": 1.007528
  },
  {
    "time_start": "2025-11-16T20:00:00+01:00",
    "SEK_per_kWh": 0.83226
  },
  {
    "time_start": "2025-11-16T21:00:00+01:00",
    "SEK_per_kWh": 0.72783
  },
  {
    "time_start": "2025-11-16T22:00:00+01:00",
    "SEK_per_kWh": 0.699703
  },
  {
    "time_start": "2025-11-16T23:00:00+01:00",
    "SEK_per_kWh": 0.494935
  }
]